CloverDBLib/__init__.py
CloverDBLib/main.py
cleverdb-0.0.1.dist-info/METADATA
cleverdb-0.0.1.dist-info/WHEEL
cleverdb-0.0.1.dist-info/top_level.txt
cleverdb-0.0.1.dist-info/RECORD
