Metadata-Version: 2.1
Name: cleverdb
Version: 0.0.1
Summary: A simple wrapper for working with SQLite in Python
Home-page: https://github.com/reques6e/CloverDB
Author: reques6e
Author-email: none@gmail.com
License: UNKNOWN
Project-URL: GitHub, https://github.com/reques6e/CloverDB
Keywords: sqlite sqlite3 database wrapper sql
Platform: UNKNOWN
Classifier: Programming Language :: Python :: 3.9
Classifier: License :: OSI Approved :: MIT License
Classifier: Operating System :: OS Independent
Requires-Python: >=3.6
